jsondt.py
jsondt-1.0.0.dist-info/LICENSE
jsondt-1.0.0.dist-info/METADATA
jsondt-1.0.0.dist-info/WHEEL
jsondt-1.0.0.dist-info/top_level.txt
jsondt-1.0.0.dist-info/RECORD
