Metadata-Version: 2.1
Name: jsondt
Version: 1.0.0
Summary: JSON module with added datetime support.
Home-page: https://github.com/zeth/jsondt
Author: Zeth Green
Author-email: theology@gmail.com
License: BSD
Platform: UNKNOWN
Classifier: Programming Language :: Python :: 3.7
Classifier: Intended Audience :: Developers
Classifier: License :: OSI Approved :: Apache Software License
Classifier: Topic :: Software Development :: Libraries
Classifier: Topic :: Utilities
Classifier: Topic :: Internet :: WWW/HTTP
Classifier: Operating System :: POSIX :: Linux
Classifier: Operating System :: Microsoft :: Windows
Classifier: Operating System :: MacOS :: MacOS X
